pytroids/__init__.py
pytroids/cyber/important_names.py
pytroids/cyber/windows_file_attrib_setters.py
pytroids/numbers/fibbonaccis.py
pytroids/numbers/number_type_verify.py
pytroids/numbers/numberS_type_verification.py
pytroids/numbers/numericals.py
pytroids/strings/lists.py
pytroids-0.2.1.dist-info/METADATA
pytroids-0.2.1.dist-info/WHEEL
pytroids-0.2.1.dist-info/RECORD
